MANIFEST.in
README.mkd
runtests.py
settings.py
setup.py
django_email_manager.egg-info/PKG-INFO
django_email_manager.egg-info/SOURCES.txt
django_email_manager.egg-info/dependency_links.txt
django_email_manager.egg-info/requires.txt
django_email_manager.egg-info/top_level.txt
email_manager/__init__.py
email_manager/admin.py
email_manager/feature_send_email.py
email_manager/feature_update_statistics.py
email_manager/feature_user_email_preferences.py
email_manager/models.py
email_manager/tasks.py
email_manager/urls.py
email_manager/management/__init__.py
email_manager/management/commands/__init__.py
email_manager/management/commands/update_email_statistics.py
email_manager/templates/base.html
email_manager/templates/email_manager/define_email_preferences.html
email_manager/templates/email_manager/send_email.html
email_manager/tests/__init__.py
email_manager/tests/test_feature_send_email.py
email_manager/tests/test_feature_update_statistics.py
email_manager/tests/test_models.py