Metadata-Version: 1.0
Name: django-email-manager
Version: 0.2.1
Summary: A simple application to store a summary of system e-mails.
Home-page: https://github.com/paulocheque/django-email-manager
Author: paulocheque
Author-email: paulocheque@gmail.com
License: MIT
Keywords: python django email
Platform: UNKNOWN
Classifier: Framework :: Django
Classifier: Operating System :: OS Independent
Classifier: Topic :: Software Development
